{
"type": "FeatureCollection",
"name": "Sinipian_Sta_Teresita",
"crs": { "type": "name", "properties": { "name": "urn:ogc:def:crs:OGC:1.3:CRS84" } },
"features": [
{ "type": "Feature", "properties": { "id": null }, "geometry": { "type": "Point", "coordinates": [ 120.968947250143927, 13.87566001361003 ] } }
]
}
